CODE_OF_CONDUCT.md
CONTRIBUTING.md
LICENSE
NOTICE
README.md
mlm-scoring.png
setup.py
examples/asr-librispeech-espnet/README.md
examples/asr-librispeech-espnet/scripts
examples/asr-librispeech-espnet/data/dev-clean.am.json
examples/asr-librispeech-espnet/data/dev-other.am.json
examples/asr-librispeech-espnet/data/test-clean.am.json
examples/asr-librispeech-espnet/data/test-other.am.json
examples/demo/format.json
examples/lingacc-blimp/README.md
examples/lingacc-blimp/accuracy.py
examples/lingacc-blimp/convert_to_dataset.py
examples/lingacc-blimp/convert_to_txt.py
examples/nmt-tedtalks-ace/README.md
examples/nmt-tedtalks-ace/data/en2vi/nbest/dev.en.bpe.beam_trans.nobpe
examples/nmt-tedtalks-ace/data/en2vi/nbest/test.en.bpe.beam_trans.nobpe
scripts/librispeech-download-text.sh
scripts/librispeech-score.sh
src/mlm/__init__.py
src/mlm/batchify.py
src/mlm/cmds.py
src/mlm/loaders.py
src/mlm/scorers.py
src/mlm/models/__init__.py
src/mlm/models/bert.py
src/mlm/models/gpt2.py
src/mlm_hashformers.egg-info/PKG-INFO
src/mlm_hashformers.egg-info/SOURCES.txt
src/mlm_hashformers.egg-info/dependency_links.txt
src/mlm_hashformers.egg-info/entry_points.txt
src/mlm_hashformers.egg-info/not-zip-safe
src/mlm_hashformers.egg-info/requires.txt
src/mlm_hashformers.egg-info/top_level.txt
tests/test_cmds.py
tests/test_loaders.py
tests/test_models.py
tests/test_scorers.py