Metadata-Version: 2.1
Name: mlm-hashformers
Version: 0.1
Summary: Masked Language Model Scoring
Home-page: UNKNOWN
Author: Julian Salazar
License: UNKNOWN
Platform: UNKNOWN
Provides-Extra: dev
License-File: LICENSE
License-File: NOTICE
